setup.py
blachnio/__init__.py
blachnio/ds.py
blachnio/utils.py
blachnio.egg-info/PKG-INFO
blachnio.egg-info/SOURCES.txt
blachnio.egg-info/dependency_links.txt
blachnio.egg-info/top_level.txt