Metadata-Version: 2.1
Name: blachnio
Version: 0.2.2
Summary: Artur Tools for everyday operations
Home-page: https://github.com/ArturBlachnio/ArturBlachnio.git
Author: Artur B
Author-email: blachnio.artur@gmail.com
License: UNKNOWN
Platform: UNKNOWN
